{
  "strategy_name": "E0V1E",
  "params": {
    "stoploss": {
      "stoploss": -0.07
    },
    "trailing": {
      "trailing_stop": false,
      "trailing_stop_positive": null,
      "trailing_stop_positive_offset": 0.0,
      "trailing_only_offset_is_reached": false
    },
    "max_open_trades": {
      "max_open_trades": 3
    },
    "buy": {
      "buy_cti_32": -0.78,
      "buy_rsi_32": 19,
      "buy_rsi_fast_32": 40,
      "buy_sma15_32": 0.9
    },
    "sell": {},
    "protection": {},
    "roi": {
      "0": 0.115,
      "11": 0.101,
      "44": 0.037,
      "61": 0
    }
  },
  "ft_stratparam_v": 1,
  "export_time": "2023-10-03 17:38:46.531724+00:00"
}