{
  "strategy_name": "E0V1E",
  "params": {
    "stoploss": {
      "stoploss": -0.18
    },
    "trailing": {
      "trailing_stop": false,
      "trailing_stop_positive": null,
      "trailing_stop_positive_offset": 0.0,
      "trailing_only_offset_is_reached": false
    },
    "max_open_trades": {
      "max_open_trades": 40
    },
    "buy": {
      "buy_cti_32": -0.11,
      "buy_rsi_32": 40,
      "buy_rsi_fast_32": 21,
      "buy_sma15_32": 0.913
    },
    "sell": {
      "sell_fastx": 75
    },
    "protection": {},
    "roi": {
      "0": 0.099,
      "36": 0.079,
      "84": 0.011,
      "98": 0
    }
  },
  "ft_stratparam_v": 1,
  "export_time": "2024-01-11 16:19:38.068699+00:00"
}